<?xml version="1.0" encoding="utf-8"?>
<ArrayOfTask xmlns:xsi="http://www.w3.org/2001/XMLSchema-instance" xmlns:xsd="http://www.w3.org/2001/XMLSchema">
  <Task>
    <Id>1</Id>
    <Alias>T1</Alias>
    <Description>428</Description>
    <CreatedAtDate>2024-02-22T23:26:53.7052724+02:00</CreatedAtDate>
    <StartDate xsi:nil="true" />
    <ScheduledDate xsi:nil="true" />
    <Duration>P297DT21H27M14S</Duration>
    <DeadlineDate xsi:nil="true" />
    <CompleteDate xsi:nil="true" />
    <Product>428428</Product>
    <Remarks>28</Remarks>
    <EngineerId xsi:nil="true" />
    <Complexity>ADVANCED_BEGGINER</Complexity>
  </Task>
  <Task>
    <Id>2</Id>
    <Alias>T2</Alias>
    <Description>447</Description>
    <CreatedAtDate>2024-02-22T23:26:53.739338+02:00</CreatedAtDate>
    <StartDate xsi:nil="true" />
    <ScheduledDate xsi:nil="true" />
    <Duration>P17DT22H14M37S</Duration>
    <DeadlineDate xsi:nil="true" />
    <CompleteDate xsi:nil="true" />
    <Product>447447</Product>
    <Remarks>47</Remarks>
    <EngineerId xsi:nil="true" />
    <Complexity>INTERMEDIATE</Complexity>
  </Task>
  <Task>
    <Id>3</Id>
    <Alias>T3</Alias>
    <Description>450</Description>
    <CreatedAtDate>2024-02-22T23:26:53.7520713+02:00</CreatedAtDate>
    <StartDate xsi:nil="true" />
    <ScheduledDate xsi:nil="true" />
    <Duration>P259DT19H54M14S</Duration>
    <DeadlineDate xsi:nil="true" />
    <CompleteDate xsi:nil="true" />
    <Product>450450</Product>
    <Remarks>50</Remarks>
    <EngineerId xsi:nil="true" />
    <Complexity>BEGGINER</Complexity>
  </Task>
  <Task>
    <Id>4</Id>
    <Alias>T4</Alias>
    <Description>435</Description>
    <CreatedAtDate>2024-02-22T23:26:53.7613178+02:00</CreatedAtDate>
    <StartDate xsi:nil="true" />
    <ScheduledDate xsi:nil="true" />
    <Duration>P298DT20H45M10S</Duration>
    <DeadlineDate xsi:nil="true" />
    <CompleteDate xsi:nil="true" />
    <Product>435435</Product>
    <Remarks>35</Remarks>
    <EngineerId xsi:nil="true" />
    <Complexity>INTERMEDIATE</Complexity>
  </Task>
  <Task>
    <Id>5</Id>
    <Alias>T5</Alias>
    <Description>435</Description>
    <CreatedAtDate>2024-02-22T23:26:53.7709901+02:00</CreatedAtDate>
    <StartDate xsi:nil="true" />
    <ScheduledDate xsi:nil="true" />
    <Duration>P32DT6H35M40S</Duration>
    <DeadlineDate xsi:nil="true" />
    <CompleteDate xsi:nil="true" />
    <Product>435435</Product>
    <Remarks>35</Remarks>
    <EngineerId xsi:nil="true" />
    <Complexity>INTERMEDIATE</Complexity>
  </Task>
  <Task>
    <Id>6</Id>
    <Alias>T6</Alias>
    <Description>424</Description>
    <CreatedAtDate>2024-02-22T23:26:53.7810281+02:00</CreatedAtDate>
    <StartDate xsi:nil="true" />
    <ScheduledDate xsi:nil="true" />
    <Duration>P91DT10H27M39S</Duration>
    <DeadlineDate xsi:nil="true" />
    <CompleteDate xsi:nil="true" />
    <Product>424424</Product>
    <Remarks>24</Remarks>
    <EngineerId xsi:nil="true" />
    <Complexity>INTERMEDIATE</Complexity>
  </Task>
  <Task>
    <Id>7</Id>
    <Alias>T7</Alias>
    <Description>420</Description>
    <CreatedAtDate>2024-02-22T23:26:53.7957558+02:00</CreatedAtDate>
    <StartDate xsi:nil="true" />
    <ScheduledDate xsi:nil="true" />
    <Duration>PT7H1M15S</Duration>
    <DeadlineDate xsi:nil="true" />
    <CompleteDate xsi:nil="true" />
    <Product>420420</Product>
    <Remarks>20</Remarks>
    <EngineerId xsi:nil="true" />
    <Complexity>ADVANCED_BEGGINER</Complexity>
  </Task>
  <Task>
    <Id>8</Id>
    <Alias>T8</Alias>
    <Description>433</Description>
    <CreatedAtDate>2024-02-22T23:26:53.8047546+02:00</CreatedAtDate>
    <StartDate xsi:nil="true" />
    <ScheduledDate xsi:nil="true" />
    <Duration>P46DT8H28M43S</Duration>
    <DeadlineDate xsi:nil="true" />
    <CompleteDate xsi:nil="true" />
    <Product>433433</Product>
    <Remarks>33</Remarks>
    <EngineerId xsi:nil="true" />
    <Complexity>ADVANCED_BEGGINER</Complexity>
  </Task>
  <Task>
    <Id>9</Id>
    <Alias>T9</Alias>
    <Description>418</Description>
    <CreatedAtDate>2024-02-22T23:26:53.814961+02:00</CreatedAtDate>
    <StartDate xsi:nil="true" />
    <ScheduledDate xsi:nil="true" />
    <Duration>P222DT10H28M</Duration>
    <DeadlineDate xsi:nil="true" />
    <CompleteDate xsi:nil="true" />
    <Product>418418</Product>
    <Remarks>18</Remarks>
    <EngineerId xsi:nil="true" />
    <Complexity>BEGGINER</Complexity>
  </Task>
  <Task>
    <Id>10</Id>
    <Alias>T10</Alias>
    <Description>455</Description>
    <CreatedAtDate>2024-02-22T23:26:53.8299881+02:00</CreatedAtDate>
    <StartDate xsi:nil="true" />
    <ScheduledDate xsi:nil="true" />
    <Duration>P146DT11H37M21S</Duration>
    <DeadlineDate xsi:nil="true" />
    <CompleteDate xsi:nil="true" />
    <Product>455455</Product>
    <Remarks>55</Remarks>
    <EngineerId xsi:nil="true" />
    <Complexity>BEGGINER</Complexity>
  </Task>
  <Task>
    <Id>11</Id>
    <Alias>T11</Alias>
    <Description>415</Description>
    <CreatedAtDate>2024-02-22T23:26:53.8442493+02:00</CreatedAtDate>
    <StartDate xsi:nil="true" />
    <ScheduledDate xsi:nil="true" />
    <Duration>P181DT41M38S</Duration>
    <DeadlineDate xsi:nil="true" />
    <CompleteDate xsi:nil="true" />
    <Product>415415</Product>
    <Remarks>15</Remarks>
    <EngineerId xsi:nil="true" />
    <Complexity>ADVANCED_BEGGINER</Complexity>
  </Task>
  <Task>
    <Id>12</Id>
    <Alias>T12</Alias>
    <Description>419</Description>
    <CreatedAtDate>2024-02-22T23:26:53.8565604+02:00</CreatedAtDate>
    <StartDate xsi:nil="true" />
    <ScheduledDate xsi:nil="true" />
    <Duration>P104DT8H46M14S</Duration>
    <DeadlineDate xsi:nil="true" />
    <CompleteDate xsi:nil="true" />
    <Product>419419</Product>
    <Remarks>19</Remarks>
    <EngineerId xsi:nil="true" />
    <Complexity>ADVANCED_BEGGINER</Complexity>
  </Task>
  <Task>
    <Id>13</Id>
    <Alias>T13</Alias>
    <Description>445</Description>
    <CreatedAtDate>2024-02-22T23:26:53.8681269+02:00</CreatedAtDate>
    <StartDate xsi:nil="true" />
    <ScheduledDate xsi:nil="true" />
    <Duration>P152DT19H39M18S</Duration>
    <DeadlineDate xsi:nil="true" />
    <CompleteDate xsi:nil="true" />
    <Product>445445</Product>
    <Remarks>45</Remarks>
    <EngineerId xsi:nil="true" />
    <Complexity>INTERMEDIATE</Complexity>
  </Task>
  <Task>
    <Id>14</Id>
    <Alias>T14</Alias>
    <Description>433</Description>
    <CreatedAtDate>2024-02-22T23:26:53.8808796+02:00</CreatedAtDate>
    <StartDate xsi:nil="true" />
    <ScheduledDate xsi:nil="true" />
    <Duration>P67DT9H40M23S</Duration>
    <DeadlineDate xsi:nil="true" />
    <CompleteDate xsi:nil="true" />
    <Product>433433</Product>
    <Remarks>33</Remarks>
    <EngineerId xsi:nil="true" />
    <Complexity>ADVANCED_BEGGINER</Complexity>
  </Task>
  <Task>
    <Id>15</Id>
    <Alias>T15</Alias>
    <Description>432</Description>
    <CreatedAtDate>2024-02-22T23:26:53.8980219+02:00</CreatedAtDate>
    <StartDate xsi:nil="true" />
    <ScheduledDate xsi:nil="true" />
    <Duration>P82DT19H21M53S</Duration>
    <DeadlineDate xsi:nil="true" />
    <CompleteDate xsi:nil="true" />
    <Product>432432</Product>
    <Remarks>32</Remarks>
    <EngineerId xsi:nil="true" />
    <Complexity>BEGGINER</Complexity>
  </Task>
  <Task>
    <Id>16</Id>
    <Alias>T16</Alias>
    <Description>437</Description>
    <CreatedAtDate>2024-02-22T23:26:53.9124221+02:00</CreatedAtDate>
    <StartDate xsi:nil="true" />
    <ScheduledDate xsi:nil="true" />
    <Duration>P29DT18H22M39S</Duration>
    <DeadlineDate xsi:nil="true" />
    <CompleteDate xsi:nil="true" />
    <Product>437437</Product>
    <Remarks>37</Remarks>
    <EngineerId xsi:nil="true" />
    <Complexity>ADVANCED_BEGGINER</Complexity>
  </Task>
  <Task>
    <Id>17</Id>
    <Alias>T17</Alias>
    <Description>438</Description>
    <CreatedAtDate>2024-02-22T23:26:53.926386+02:00</CreatedAtDate>
    <StartDate xsi:nil="true" />
    <ScheduledDate xsi:nil="true" />
    <Duration>P344DT17H3M20S</Duration>
    <DeadlineDate xsi:nil="true" />
    <CompleteDate xsi:nil="true" />
    <Product>438438</Product>
    <Remarks>38</Remarks>
    <EngineerId xsi:nil="true" />
    <Complexity>BEGGINER</Complexity>
  </Task>
  <Task>
    <Id>18</Id>
    <Alias>T18</Alias>
    <Description>416</Description>
    <CreatedAtDate>2024-02-22T23:26:53.9412304+02:00</CreatedAtDate>
    <StartDate xsi:nil="true" />
    <ScheduledDate xsi:nil="true" />
    <Duration>P343DT4H58M21S</Duration>
    <DeadlineDate xsi:nil="true" />
    <CompleteDate xsi:nil="true" />
    <Product>416416</Product>
    <Remarks>16</Remarks>
    <EngineerId xsi:nil="true" />
    <Complexity>ADVANCED_BEGGINER</Complexity>
  </Task>
  <Task>
    <Id>20</Id>
    <Alias>T20</Alias>
    <Description>412</Description>
    <CreatedAtDate>2024-02-22T23:26:53.9664045+02:00</CreatedAtDate>
    <StartDate xsi:nil="true" />
    <ScheduledDate xsi:nil="true" />
    <Duration>P112DT20H54M57S</Duration>
    <DeadlineDate xsi:nil="true" />
    <CompleteDate xsi:nil="true" />
    <Product>412412</Product>
    <Remarks>12</Remarks>
    <EngineerId xsi:nil="true" />
    <Complexity>INTERMEDIATE</Complexity>
  </Task>
  <Task>
    <Id>21</Id>
    <Alias>T1</Alias>
    <Description>432</Description>
    <CreatedAtDate>2024-02-22T23:27:03.1150548+02:00</CreatedAtDate>
    <StartDate xsi:nil="true" />
    <ScheduledDate xsi:nil="true" />
    <Duration>P159DT15H1M11S</Duration>
    <DeadlineDate xsi:nil="true" />
    <CompleteDate xsi:nil="true" />
    <Product>432432</Product>
    <Remarks>32</Remarks>
    <EngineerId xsi:nil="true" />
    <Complexity>BEGGINER</Complexity>
  </Task>
  <Task>
    <Id>22</Id>
    <Alias>T2</Alias>
    <Description>425</Description>
    <CreatedAtDate>2024-02-22T23:27:03.1559106+02:00</CreatedAtDate>
    <StartDate xsi:nil="true" />
    <ScheduledDate xsi:nil="true" />
    <Duration>P360DT2H32M14S</Duration>
    <DeadlineDate xsi:nil="true" />
    <CompleteDate xsi:nil="true" />
    <Product>425425</Product>
    <Remarks>25</Remarks>
    <EngineerId xsi:nil="true" />
    <Complexity>ADVANCED_BEGGINER</Complexity>
  </Task>
  <Task>
    <Id>23</Id>
    <Alias>T3</Alias>
    <Description>433</Description>
    <CreatedAtDate>2024-02-22T23:27:03.1639261+02:00</CreatedAtDate>
    <StartDate xsi:nil="true" />
    <ScheduledDate xsi:nil="true" />
    <Duration>P118DT21H1M39S</Duration>
    <DeadlineDate xsi:nil="true" />
    <CompleteDate xsi:nil="true" />
    <Product>433433</Product>
    <Remarks>33</Remarks>
    <EngineerId xsi:nil="true" />
    <Complexity>INTERMEDIATE</Complexity>
  </Task>
  <Task>
    <Id>24</Id>
    <Alias>T4</Alias>
    <Description>424</Description>
    <CreatedAtDate>2024-02-22T23:27:03.1770807+02:00</CreatedAtDate>
    <StartDate xsi:nil="true" />
    <ScheduledDate xsi:nil="true" />
    <Duration>P141DT15H45M25S</Duration>
    <DeadlineDate xsi:nil="true" />
    <CompleteDate xsi:nil="true" />
    <Product>424424</Product>
    <Remarks>24</Remarks>
    <EngineerId xsi:nil="true" />
    <Complexity>BEGGINER</Complexity>
  </Task>
  <Task>
    <Id>25</Id>
    <Alias>T5</Alias>
    <Description>432</Description>
    <CreatedAtDate>2024-02-22T23:27:03.1892917+02:00</CreatedAtDate>
    <StartDate xsi:nil="true" />
    <ScheduledDate xsi:nil="true" />
    <Duration>P77DT1H48M46S</Duration>
    <DeadlineDate xsi:nil="true" />
    <CompleteDate xsi:nil="true" />
    <Product>432432</Product>
    <Remarks>32</Remarks>
    <EngineerId xsi:nil="true" />
    <Complexity>ADVANCED_BEGGINER</Complexity>
  </Task>
  <Task>
    <Id>26</Id>
    <Alias>T6</Alias>
    <Description>457</Description>
    <CreatedAtDate>2024-02-22T23:27:03.2025529+02:00</CreatedAtDate>
    <StartDate xsi:nil="true" />
    <ScheduledDate xsi:nil="true" />
    <Duration>P53DT3H4M30S</Duration>
    <DeadlineDate xsi:nil="true" />
    <CompleteDate xsi:nil="true" />
    <Product>457457</Product>
    <Remarks>57</Remarks>
    <EngineerId xsi:nil="true" />
    <Complexity>INTERMEDIATE</Complexity>
  </Task>
  <Task>
    <Id>27</Id>
    <Alias>T7</Alias>
    <Description>454</Description>
    <CreatedAtDate>2024-02-22T23:27:03.217088+02:00</CreatedAtDate>
    <StartDate xsi:nil="true" />
    <ScheduledDate xsi:nil="true" />
    <Duration>P9DT11H47M</Duration>
    <DeadlineDate xsi:nil="true" />
    <CompleteDate xsi:nil="true" />
    <Product>454454</Product>
    <Remarks>54</Remarks>
    <EngineerId xsi:nil="true" />
    <Complexity>BEGGINER</Complexity>
  </Task>
  <Task>
    <Id>28</Id>
    <Alias>T8</Alias>
    <Description>442</Description>
    <CreatedAtDate>2024-02-22T23:27:03.2310389+02:00</CreatedAtDate>
    <StartDate xsi:nil="true" />
    <ScheduledDate xsi:nil="true" />
    <Duration>P24DT14H37M11S</Duration>
    <DeadlineDate xsi:nil="true" />
    <CompleteDate xsi:nil="true" />
    <Product>442442</Product>
    <Remarks>42</Remarks>
    <EngineerId xsi:nil="true" />
    <Complexity>ADVANCED_BEGGINER</Complexity>
  </Task>
  <Task>
    <Id>29</Id>
    <Alias>T9</Alias>
    <Description>423</Description>
    <CreatedAtDate>2024-02-22T23:27:03.2410558+02:00</CreatedAtDate>
    <StartDate xsi:nil="true" />
    <ScheduledDate xsi:nil="true" />
    <Duration>P137DT10H28M5S</Duration>
    <DeadlineDate xsi:nil="true" />
    <CompleteDate xsi:nil="true" />
    <Product>423423</Product>
    <Remarks>23</Remarks>
    <EngineerId xsi:nil="true" />
    <Complexity>INTERMEDIATE</Complexity>
  </Task>
  <Task>
    <Id>30</Id>
    <Alias>T10</Alias>
    <Description>417</Description>
    <CreatedAtDate>2024-02-22T23:27:03.2548202+02:00</CreatedAtDate>
    <StartDate xsi:nil="true" />
    <ScheduledDate xsi:nil="true" />
    <Duration>P135DT2H6M51S</Duration>
    <DeadlineDate xsi:nil="true" />
    <CompleteDate xsi:nil="true" />
    <Product>417417</Product>
    <Remarks>17</Remarks>
    <EngineerId xsi:nil="true" />
    <Complexity>INTERMEDIATE</Complexity>
  </Task>
  <Task>
    <Id>31</Id>
    <Alias>T11</Alias>
    <Description>430</Description>
    <CreatedAtDate>2024-02-22T23:27:03.2666585+02:00</CreatedAtDate>
    <StartDate xsi:nil="true" />
    <ScheduledDate xsi:nil="true" />
    <Duration>P294DT10H47M57S</Duration>
    <DeadlineDate xsi:nil="true" />
    <CompleteDate xsi:nil="true" />
    <Product>430430</Product>
    <Remarks>30</Remarks>
    <EngineerId xsi:nil="true" />
    <Complexity>INTERMEDIATE</Complexity>
  </Task>
  <Task>
    <Id>32</Id>
    <Alias>T12</Alias>
    <Description>422</Description>
    <CreatedAtDate>2024-02-22T23:27:03.2821428+02:00</CreatedAtDate>
    <StartDate xsi:nil="true" />
    <ScheduledDate xsi:nil="true" />
    <Duration>P234DT11H8M49S</Duration>
    <DeadlineDate xsi:nil="true" />
    <CompleteDate xsi:nil="true" />
    <Product>422422</Product>
    <Remarks>22</Remarks>
    <EngineerId xsi:nil="true" />
    <Complexity>ADVANCED_BEGGINER</Complexity>
  </Task>
  <Task>
    <Id>33</Id>
    <Alias>T13</Alias>
    <Description>437</Description>
    <CreatedAtDate>2024-02-22T23:27:03.2950178+02:00</CreatedAtDate>
    <StartDate xsi:nil="true" />
    <ScheduledDate xsi:nil="true" />
    <Duration>P316DT2H34M20S</Duration>
    <DeadlineDate xsi:nil="true" />
    <CompleteDate xsi:nil="true" />
    <Product>437437</Product>
    <Remarks>37</Remarks>
    <EngineerId xsi:nil="true" />
    <Complexity>BEGGINER</Complexity>
  </Task>
  <Task>
    <Id>34</Id>
    <Alias>T14</Alias>
    <Description>467</Description>
    <CreatedAtDate>2024-02-22T23:27:03.3042775+02:00</CreatedAtDate>
    <StartDate xsi:nil="true" />
    <ScheduledDate xsi:nil="true" />
    <Duration>P34DT16H3M50S</Duration>
    <DeadlineDate xsi:nil="true" />
    <CompleteDate xsi:nil="true" />
    <Product>467467</Product>
    <Remarks>67</Remarks>
    <EngineerId xsi:nil="true" />
    <Complexity>INTERMEDIATE</Complexity>
  </Task>
  <Task>
    <Id>35</Id>
    <Alias>T15</Alias>
    <Description>423</Description>
    <CreatedAtDate>2024-02-22T23:27:03.313992+02:00</CreatedAtDate>
    <StartDate xsi:nil="true" />
    <ScheduledDate xsi:nil="true" />
    <Duration>P291DT16H47M39S</Duration>
    <DeadlineDate xsi:nil="true" />
    <CompleteDate xsi:nil="true" />
    <Product>423423</Product>
    <Remarks>23</Remarks>
    <EngineerId xsi:nil="true" />
    <Complexity>INTERMEDIATE</Complexity>
  </Task>
  <Task>
    <Id>36</Id>
    <Alias>T16</Alias>
    <Description>450</Description>
    <CreatedAtDate>2024-02-22T23:27:03.3244852+02:00</CreatedAtDate>
    <StartDate xsi:nil="true" />
    <ScheduledDate xsi:nil="true" />
    <Duration>P23DT19H49M28S</Duration>
    <DeadlineDate xsi:nil="true" />
    <CompleteDate xsi:nil="true" />
    <Product>450450</Product>
    <Remarks>50</Remarks>
    <EngineerId xsi:nil="true" />
    <Complexity>ADVANCED_BEGGINER</Complexity>
  </Task>
  <Task>
    <Id>37</Id>
    <Alias>T17</Alias>
    <Description>444</Description>
    <CreatedAtDate>2024-02-22T23:27:03.3336318+02:00</CreatedAtDate>
    <StartDate xsi:nil="true" />
    <ScheduledDate xsi:nil="true" />
    <Duration>P338DT21H27M20S</Duration>
    <DeadlineDate xsi:nil="true" />
    <CompleteDate xsi:nil="true" />
    <Product>444444</Product>
    <Remarks>44</Remarks>
    <EngineerId xsi:nil="true" />
    <Complexity>INTERMEDIATE</Complexity>
  </Task>
  <Task>
    <Id>38</Id>
    <Alias>T18</Alias>
    <Description>418</Description>
    <CreatedAtDate>2024-02-22T23:27:03.3429796+02:00</CreatedAtDate>
    <StartDate xsi:nil="true" />
    <ScheduledDate xsi:nil="true" />
    <Duration>P15DT9H21M11S</Duration>
    <DeadlineDate xsi:nil="true" />
    <CompleteDate xsi:nil="true" />
    <Product>418418</Product>
    <Remarks>18</Remarks>
    <EngineerId xsi:nil="true" />
    <Complexity>ADVANCED_BEGGINER</Complexity>
  </Task>
  <Task>
    <Id>39</Id>
    <Alias>T19</Alias>
    <Description>436</Description>
    <CreatedAtDate>2024-02-22T23:27:03.3538047+02:00</CreatedAtDate>
    <StartDate xsi:nil="true" />
    <ScheduledDate xsi:nil="true" />
    <Duration>P235DT8H48M17S</Duration>
    <DeadlineDate xsi:nil="true" />
    <CompleteDate xsi:nil="true" />
    <Product>436436</Product>
    <Remarks>36</Remarks>
    <EngineerId xsi:nil="true" />
    <Complexity>BEGGINER</Complexity>
  </Task>
  <Task>
    <Id>40</Id>
    <Alias>T20</Alias>
    <Description>404</Description>
    <CreatedAtDate>2024-02-22T23:27:03.3700236+02:00</CreatedAtDate>
    <StartDate xsi:nil="true" />
    <ScheduledDate xsi:nil="true" />
    <Duration>P27DT8H36M44S</Duration>
    <DeadlineDate xsi:nil="true" />
    <CompleteDate xsi:nil="true" />
    <Product>404404</Product>
    <Remarks>04</Remarks>
    <EngineerId xsi:nil="true" />
    <Complexity>BEGGINER</Complexity>
  </Task>
  <Task>
    <Id>19</Id>
    <Alias>T19</Alias>
    <Description>458</Description>
    <CreatedAtDate>2024-02-22T23:26:53.952006+02:00</CreatedAtDate>
    <StartDate xsi:nil="true" />
    <ScheduledDate xsi:nil="true" />
    <Duration>P17DT17H41M18S</Duration>
    <DeadlineDate xsi:nil="true" />
    <CompleteDate xsi:nil="true" />
    <Product>458458</Product>
    <Remarks>58</Remarks>
    <EngineerId xsi:nil="true" />
    <Complexity>BEGGINER</Complexity>
  </Task>
</ArrayOfTask>